nipreps/__init__.py
nipreps-1.0.dist-info/LICENSE
nipreps-1.0.dist-info/WHEEL
nipreps-1.0.dist-info/METADATA
nipreps-1.0.dist-info/RECORD
