Metadata-Version: 2.1
Name: nipreps
Version: 1.0
Summary: Namespace package for nipreps utilities
Author-email: The Nipreps developers <nipreps@gmail.com>
Classifier: License :: OSI Approved :: Apache Software License
Project-URL: Home, https://nipreps.org
Project-URL: Source Code, https://github.com/nipreps/nipreps
